{
    "commits_count": 138,
    "date_started": "2019-04-19",
    "date_updated": "2025-06-21",
    "description": "Top disclosed reports from HackerOne",
    "forks_count": 843,
    "html_url": "https://github.com/reddelexc/hackerone-reports",
    "keywords": [
        "xxe",
        "ssrf"
    ],
    "language": "Python",
    "repo_name": "hackerone-reports",
    "repo_owner": "reddelexc",
    "repotime": "2025-06-21, 21:21:52",
    "stargazers_count": 4655,
    "watchers_count": 4655
}
{
    "commits_count": 178,
    "date_started": "2024-05-30",
    "date_updated": "2025-06-20",
    "description": "Fourth evolution of Code Injection for Xcode",
    "forks_count": 7,
    "html_url": "https://github.com/johnno1962/InjectionNext",
    "keywords": [
        "code injection"
    ],
    "language": "Swift",
    "repo_name": "InjectionNext",
    "repo_owner": "johnno1962",
    "repotime": "2025-06-20, 19:36:40",
    "stargazers_count": 185,
    "watchers_count": 185
}
{
    "commits_count": 229,
    "date_started": "2018-12-19",
    "date_updated": "2025-06-11",
    "description": "TypeScript clients for databases that prevent SQL Injection",
    "forks_count": 46,
    "html_url": "https://github.com/ForbesLindesay/atdatabases",
    "keywords": [
        "sql injection"
    ],
    "language": "TypeScript",
    "repo_name": "atdatabases",
    "repo_owner": "ForbesLindesay",
    "repotime": "2025-06-11, 12:07:21",
    "stargazers_count": 618,
    "watchers_count": 618
}
{
    "commits_count": 138,
    "date_started": "2019-04-19",
    "date_updated": "2025-06-21",
    "description": "Top disclosed reports from HackerOne",
    "forks_count": 843,
    "html_url": "https://github.com/reddelexc/hackerone-reports",
    "keywords": [
        "xxe",
        "ssrf"
    ],
    "language": "Python",
    "repo_name": "hackerone-reports",
    "repo_owner": "reddelexc",
    "repotime": "2025-06-21, 21:21:52",
    "stargazers_count": 4655,
    "watchers_count": 4655
}
{
    "commits_count": 178,
    "date_started": "2024-05-30",
    "date_updated": "2025-06-20",
    "description": "Fourth evolution of Code Injection for Xcode",
    "forks_count": 7,
    "html_url": "https://github.com/johnno1962/InjectionNext",
    "keywords": [
        "code injection"
    ],
    "language": "Swift",
    "repo_name": "InjectionNext",
    "repo_owner": "johnno1962",
    "repotime": "2025-06-20, 19:36:40",
    "stargazers_count": 185,
    "watchers_count": 185
}
