{
    "commits_count": 51,
    "date_started": "2024-03-31",
    "date_updated": "2024-04-01",
    "description": "Code and data for the essay &amp;quot;General equilibrium analysis of the effect of RCEP on trade flow and welfare&amp;quot;.",
    "forks_count": 1,
    "html_url": "https://github.com/Sherrylhs/RCEP-research",
    "keywords": [
        "rce analysis"
    ],
    "language": "Stata",
    "repo_name": "RCEP-research",
    "repo_owner": "Sherrylhs",
    "repotime": "2024-04-01, 18:38:21",
    "stargazers_count": 2,
    "watchers_count": 2
}
{
    "commits_count": 51,
    "date_started": "2024-03-31",
    "date_updated": "2024-04-01",
    "description": "Code and data for the essay &amp;quot;General equilibrium analysis of the effect of RCEP on trade flow and welfare&amp;quot;.",
    "forks_count": 1,
    "html_url": "https://github.com/Sherrylhs/RCEP-research",
    "keywords": [
        "rce analysis"
    ],
    "language": "Stata",
    "repo_name": "RCEP-research",
    "repo_owner": "Sherrylhs",
    "repotime": "2024-04-01, 18:38:21",
    "stargazers_count": 2,
    "watchers_count": 2
}
{
    "commits_count": 51,
    "date_started": "2024-03-31",
    "date_updated": "2024-04-01",
    "description": "Code and data for the essay &amp;quot;General equilibrium analysis of the effect of RCEP on trade flow and welfare&amp;quot;.",
    "forks_count": 1,
    "html_url": "https://github.com/Sherrylhs/RCEP-research",
    "keywords": [
        "rce analysis"
    ],
    "language": "Stata",
    "repo_name": "RCEP-research",
    "repo_owner": "Sherrylhs",
    "repotime": "2024-04-01, 18:38:21",
    "stargazers_count": 2,
    "watchers_count": 2
}
