{
    "commits_count": 7,
    "date_started": "2017-11-07",
    "date_updated": "2018-04-01",
    "description": "Remote Code Execution exploiter",
    "forks_count": 6,
    "html_url": "https://github.com/websecnl/RCE_Universal_Exploiter",
    "keywords": [
        "remote code execution exploitation",
        "remote code execution exploit"
    ],
    "language": "Python",
    "repo_name": "RCE_Universal_Exploiter",
    "repo_owner": "websecnl",
    "repotime": "2018-04-01, 12:14:55",
    "stargazers_count": 1,
    "watchers_count": 1
}
