{
    "commits_count": 3,
    "date_started": "2016-05-27",
    "date_updated": "2016-05-26",
    "description": "This repo contains code for developing client server proxy for SSH connection. Proxies will encrypt-decrypt data being exchanged between SSH client and remote host. This is a kind of extra layer of security for SSH connection to prevent zero-day vulnerability.",
    "forks_count": 0,
    "html_url": "https://github.com/harshpatel1427/PlugboardProxy",
    "keywords": [
        "zero-day vulnerability"
    ],
    "language": "C",
    "repo_name": "PlugboardProxy",
    "repo_owner": "harshpatel1427",
    "repotime": "2016-05-26, 23:57:10",
    "stargazers_count": 1,
    "watchers_count": 1
}
{
    "commits_count": 3,
    "date_started": "2016-05-27",
    "date_updated": "2016-05-26",
    "description": "This repo contains code for developing client server proxy for SSH connection. Proxies will encrypt-decrypt data being exchanged between SSH client and remote host. This is a kind of extra layer of security for SSH connection to prevent zero-day vulnerability.",
    "forks_count": 0,
    "html_url": "https://github.com/harshpatel1427/PlugboardProxy",
    "keywords": [
        "zero-day vulnerability"
    ],
    "language": "C",
    "repo_name": "PlugboardProxy",
    "repo_owner": "harshpatel1427",
    "repotime": "2016-05-26, 23:57:10",
    "stargazers_count": 1,
    "watchers_count": 1
}
