{
    "commits_count": 15,
    "date_started": "2019-03-14",
    "date_updated": "2020-09-07",
    "description": "SAP Gateway RCE exploits",
    "forks_count": 45,
    "html_url": "https://github.com/chipik/SAP_GW_RCE_exploit",
    "keywords": [
        "rce exploit",
        "rce exploitation"
    ],
    "language": "Python",
    "repo_name": "SAP_GW_RCE_exploit",
    "repo_owner": "chipik",
    "repotime": "2020-09-07, 16:46:03",
    "stargazers_count": 156,
    "watchers_count": 156
}
{
    "commits_count": 15,
    "date_started": "2020-09-05",
    "date_updated": "2020-09-05",
    "description": "Code from free Microsoft Machine Learning course. Predicts if rocket can launch using as input a dataset with a lot of weather conditions days before and after 60 rocket launches",
    "forks_count": 0,
    "html_url": "https://github.com/aleeherasimiuk/Rocket-Launch-ML",
    "keywords": [
        "Microsoft use after free"
    ],
    "language": "Jupyter Notebook",
    "repo_name": "Rocket-Launch-ML",
    "repo_owner": "aleeherasimiuk",
    "repotime": "2020-09-05, 19:23:22",
    "stargazers_count": 0,
    "watchers_count": 0
}
